spamBot101/__init__.py
spamBot101/spamCode.py
spamBot101-0.1.dist-info/LICENSE.txt
spamBot101-0.1.dist-info/METADATA
spamBot101-0.1.dist-info/WHEEL
spamBot101-0.1.dist-info/top_level.txt
spamBot101-0.1.dist-info/RECORD
