Metadata-Version: 2.1
Name: spamBot101
Version: 0.1
Summary: A simple spam bot for WhatsApp. It can spam a message a given number of times or spam forever. It can be stopped by pressing ctrl.
Home-page: https://github.com/sushil3125/Spam-Bot-using-Python
Download-URL: https://github.com/sushil3125/Spam-Bot-using-Python/blob/main/projectSpamBot.exe
Author: Sushil Dhakal
Author-email: sushilldhakal25@gmail.com
License: MIT
Classifier: Programming Language :: Python :: 3
Classifier: Programming Language :: Python :: 3.4
Classifier: Programming Language :: Python :: 3.5
Classifier: Programming Language :: Python :: 3.6
License-File: LICENSE.txt
Requires-Dist: pyautogui
